{
  "_note1": "KEEP THIS FILE! Check it into a version control system (VCS) like git.",
  "_note2": "ObjectBox manages crucial IDs for your object model. See docs for details.",
  "_note3": "If you have VCS merge conflicts, you must resolve them according to ObjectBox docs.",
  "entities": [
    {
      "id": "1:3770196133259514733",
      "lastPropertyId": "8:6080853715122793338",
      "name": "DreamStorageEntity",
      "properties": [
        {
          "id": "1:4189395883304815171",
          "name": "id"
        },
        {
          "id": "4:6417685975912563974",
          "name": "date"
        },
        {
          "id": "6:6578176199722520480",
          "name": "description"
        },
        {
          "id": "8:6080853715122793338",
          "name": "isLucid"
        }
      ],
      "relations": []
    }
  ],
  "lastEntityId": "1:3770196133259514733",
  "lastIndexId": "0:0",
  "lastRelationId": "0:0",
  "lastSequenceId": "0:0",
  "modelVersion": 4,
  "modelVersionParserMinimum": 4,
  "retiredEntityUids": [],
  "retiredIndexUids": [],
  "retiredPropertyUids": [
    3050175108932265569,
    5516453383483140599,
    5647861649402179499,
    4532994290183187535
  ],
  "retiredRelationUids": [],
  "version": 1
}